mkdocs_mini_blog/__init__.py
mkdocs_mini_blog/assets/css/bootstrap.min.css
mkdocs_mini_blog/assets/css/bootstrap.min.css.map
mkdocs_mini_blog/assets/css/grayscale-dark.min.css
mkdocs_mini_blog/assets/css/main.min.css
mkdocs_mini_blog/assets/css/media.min.css
mkdocs_mini_blog/assets/css/mkdocstrings.min.css
mkdocs_mini_blog/assets/css/root.min.css
mkdocs_mini_blog/assets/img/favicon.ico
mkdocs_mini_blog/assets/img/logo.png
mkdocs_mini_blog/assets/js/bootstrap.bundle.min.js
mkdocs_mini_blog/assets/js/bootstrap.bundle.min.js.map
mkdocs_mini_blog/assets/js/jquery-3.3.1.slim.min.js
mkdocs_mini_blog/assets/js/main.min.js
mkdocs_mini_blog/base.html
mkdocs_mini_blog/main.html
mkdocs_mini_blog/mkdocs_theme.yml
mkdocs_mini_blog/modules/content.html
mkdocs_mini_blog/modules/copyright.html
mkdocs_mini_blog/modules/dropdown-menu.html
mkdocs_mini_blog/modules/footer.html
mkdocs_mini_blog/modules/header.html
mkdocs_mini_blog/modules/menu.html
mkdocs_mini_blog/modules/preview.html
mkdocs_mini_blog/modules/search.html
mkdocs_mini_blog/modules/searchbox.html
mkdocs_mini_blog/modules/sidebar.html
mkdocs_mini_blog/modules/source.html
mkdocs_mini_blog/search.html
mkdocs_mini_blog-0.1.1.dist-info/WHEEL
mkdocs_mini_blog-0.1.1.dist-info/entry_points.txt
mkdocs_mini_blog-0.1.1.dist-info/METADATA
mkdocs_mini_blog-0.1.1.dist-info/RECORD
