Metadata-Version: 2.3
Name: mkdocs-mini-blog
Version: 0.1.1
Summary: A minimal blog theme for MkDocs, based on the MkDocs Simple Blog, by Fernando Celmer.
Author: Fernando Celmer, Dimitrios Poulopoulos
Author-email: Fernando Celmer <email@fernandocelmer.com>, Dimitrios Poulopoulos <dimitris.a.poulopoulos@gmail.com>
License: MIT License
Classifier: Development Status :: 5 - Production/Stable
Classifier: Operating System :: OS Independent
Classifier: License :: OSI Approved :: MIT License
Classifier: Intended Audience :: Developers
Classifier: Natural Language :: English
Classifier: Programming Language :: Python :: 3.9
Classifier: Programming Language :: Python :: 3.10
Classifier: Programming Language :: Python :: 3.11
Classifier: Programming Language :: Python :: 3.12
Classifier: Programming Language :: Python :: 3.13
Requires-Dist: mkdocs>=1.6.1
Requires-Python: >=3.9
Project-URL: Documentation, https://dpoulopoulos.github.io/mkdocs-mini-blog/
Project-URL: Homepage, https://github.com/dpoulopoulos/mkdocs-mini-blog
Project-URL: Issues, https://github.com/dpoulopoulos/mkdocs-mini-blog/issues
Project-URL: Repository, https://github.com/dpoulopoulos/mkdocs-mini-blog
